Workbook

Sheet 使用说明
A1: 用途 | B1: 可复算的运营与BA Excel练习；所有数据为原创虚构教学数据。
A2: 重要口径 | B2: 金额在此表以元展示；SQLite以分存储。订单财务采用截至2026-09-30退款归回原订单的分析口径。
A3: 练习方式 | B3: 先在任务页填写公式或操作，再对照参考答案；参考答案的公式与数值可以用原生Excel或LibreOffice重算。
A4: 数据边界 | B4: 库存、广告归因、流量为独立练习快照，尚未构成校准后的经营仿真或因果模型。
A5: 工具边界 | B5: 24个公式样例可重算；6个界面/Power Query任务提供操作与验收条件，不冒称已经完成界面实测。
A6: 当前日期 | B6: 2026-10-17；模拟业务观察截止2026-09-30。

Sheet 练习输入
A1: SKU | B1: 数量 | C1: 单价元 | D1: 折扣元 | E1: 单位成本元 | F1: 佣金率 | G1: 履约费元 | H1: 点击 | I1: 曝光 | J1: 广告费元 | K1: 归因销售元 | L1: 未分配可售量 | M1: 日预测 | N1: 交期天 | O1: 安全库存 | P1: MOQ | Q1: 在途 | R1: 待清理SKU | S1: 文本日期
A2: SKU001 | B2: 2 | C2: 13 | D2: 1.3 | E2: 9.24 | F2: 0.06 | G2: 6.5 | H2: 50 | I2: 1000 | J2: 100 | K2: 400 | L2: 30 | M2: 8 | N2: 7 | O2: 20 | P2: 12 | Q2: 24 | R2: SKU001 | S2: 2026-09-15
A3: SKU002 | B3: 2 | C3: 40 | D3: 4 | E3: 21.77 | F3: 0.06 | G3: 6.5 | H3: 50 | I3: 1000 | J3: 100 | K3: 400 | L3: 30 | M3: 8 | N3: 7 | O3: 20 | P3: 12 | Q3: 24 | R3: SKU002 | S3: 2026-09-15
A4: SKU003 | B4: 2 | C4: 28 | D4: 2.8 | E4: 14.86 | F4: 0.06 | G4: 6.5 | H4: 50 | I4: 1000 | J4: 100 | K4: 400 | L4: 30 | M4: 8 | N4: 7 | O4: 20 | P4: 12 | Q4: 24 | R4: SKU003 | S4: 2026-09-15
A5: SKU025 | B5: 2 | C5: 430 | D5: 43 | E5: 260.15 | F5: 0.06 | G5: 6.5 | H5: 50 | I5: 1000 | J5: 100 | K5: 400 | L5: 30 | M5: 8 | N5: 7 | O5: 20 | P5: 12 | Q5: 24 | R5: SKU025 | S5: 2026-09-15
A6: SKU026 | B6: 2 | C6: 549 | D6: 54.9 | E6: 331.74 | F6: 0.06 | G6: 6.5 | H6: 50 | I6: 1000 | J6: 100 | K6: 400 | L6: 30 | M6: 8 | N6: 7 | O6: 20 | P6: 12 | Q6: 24 | R6: SKU026 | S6: 2026-09-15
A7: SKU037 | B7: 2 | C7: 1424 | D7: 142.4 | E7: 867.97 | F7: 0.06 | G7: 6.5 | H7: 50 | I7: 1000 | J7: 100 | K7: 400 | L7: 30 | M7: 8 | N7: 7 | O7: 20 | P7: 12 | Q7: 24 | R7: SKU037 | S7: 2026-09-15
A8: SKU038 | B8: 2 | C8: 1470 | D8: 147 | E8: 1030.48 | F8: 0.06 | G8: 6.5 | H8: 50 | I8: 1000 | J8: 100 | K8: 400 | L8: 30 | M8: 8 | N8: 7 | O8: 20 | P8: 12 | Q8: 24 | R8: SKU038 | S8: 2026-09-15
A9: SKU039 | B9: 2 | C9: 1250 | D9: 125 | E9: 921.94 | F9: 0.06 | G9: 6.5 | H9: 50 | I9: 1000 | J9: 100 | K9: 400 | L9: 30 | M9: 8 | N9: 7 | O9: 20 | P9: 12 | Q9: 24 | R9: SKU039 | S9: 2026-09-15

Sheet 订单财务
A1: 订单ID | B1: 日期 | C1: 渠道 | D1: 净商品收入 | E1: 原COGS | F1: 成本回收 | G1: 佣金 | H1: 履约费 | I1: 售后费 | J1: 广告前贡献 | K1: 折扣 | L1: 折后退款前金额 | M1: 退款 | N1: 件数 | O1: 客户ID
A2: ORD0001 | B2: 46211 | C2: AMZ | D2: 116.16 | E2: 83.88 | F2: 8.39 | G2: 17.42 | H2: 6.5 | I2: 10 | J2: 6.75 | K2: 14.8 | L2: 145.2 | M2: 29.04 | N2: 8 | O2: CUS012
A3: ORD0002 | B3: 46218 | C3: STORE | D3: 2743.8 | E3: 1970.11 | F3: 0 | G3: 27.44 | H3: 42 | I3: 0 | J3: 704.25 | K3: 233.2 | L3: 2743.8 | M3: 0 | N3: 3 | O3: CUS023
A4: ORD0004 | B4: 46232 | C4: CN | D4: 2548 | E4: 1646.04 | F4: 0 | G4: 152.88 | H4: 42 | I4: 0 | J4: 707.08 | K4: 0 | L4: 2548 | M4: 0 | N4: 3 | O4: CUS045
A5: ORD0005 | B5: 46239 | C5: AMZ | D5: 1174.05 | E5: 768.66 | F5: 0 | G5: 140.89 | H5: 42 | I5: 0 | J5: 222.5 | K5: 202.95 | L5: 1174.05 | M5: 0 | N5: 7 | O5: CUS056
A6: ORD0006 | B6: 46246 | C6: STORE | D6: 1989 | E6: 1385.89 | F6: 0 | G6: 19.89 | H6: 42 | I6: 0 | J6: 541.22 | K6: 129 | L6: 1989 | M6: 0 | N6: 2 | O6: CUS007
A7: ORD0007 | B7: 46253 | C7: B2B | D7: 969.23 | E7: 757.24 | F7: 75.72 | G7: 22.03 | H7: 42 | I7: 5 | J7: 218.68 | K7: 106.6 | L7: 1101.4 | M7: 132.17 | N7: 9 | O7: CUS018
A8: ORD0008 | B8: 46260 | C8: CN | D8: 1856.4 | E8: 1276.87 | F8: 0 | G8: 111.38 | H8: 42 | I8: 0 | J8: 426.15 | K8: 25.6 | L8: 1856.4 | M8: 0 | N8: 6 | O8: CUS029
A9: ORD0009 | B9: 46267 | C9: AMZ | D9: 96.6 | E9: 72.32 | F9: 0 | G9: 11.59 | H9: 6.5 | I9: 0 | J9: 6.19 | K9: 11.4 | L9: 96.6 | M9: 0 | N9: 5 | O9: CUS040
A10: ORD0010 | B10: 46274 | C10: STORE | D10: 202.7 | E10: 122.63 | F10: 0 | G10: 2.03 | H10: 6.5 | I10: 0 | J10: 71.54 | K10: 2.3 | L10: 202.7 | M10: 0 | N10: 7 | O10: CUS051
A11: ORD0011 | B11: 46281 | C11: B2B | D11: 1888.8 | E11: 1387.31 | F11: 0 | G11: 37.78 | H11: 42 | I11: 0 | J11: 421.71 | K11: 237.2 | L11: 1888.8 | M11: 0 | N11: 2 | O11: CUS002
A12: ORD0012 | B12: 46288 | C12: CN | D12: 38.9 | E12: 36.96 | F12: 3.7 | G12: 2.65 | H12: 6.5 | I12: 5 | J12: -8.51 | K12: 7.8 | L12: 44.2 | M12: 5.3 | N12: 4 | O12: CUS013
A13: ORD0013 | B13: 46295 | C13: AMZ | D13: 2324.15 | E13: 1523.64 | F13: 0 | G13: 278.9 | H13: 42 | I13: 0 | J13: 479.61 | K13: 204.85 | L13: 2324.15 | M13: 0 | N13: 6 | O13: CUS024
... A199: ORD0240 | B199: 46228 | C199: CN | D199: 1057.2 | E199: 669.29 | F199: 0 | G199: 63.43 | H199: 42 | I199: 0 | J199: 282.48 | K199: 82.8 | L199: 1057.2 | M199: 0 | N199: 2 | O199: CUS001

Sheet 原始订单
A1: order_id | B1: order_date | C1: channel_id | D1: status | E1: customer_id
A2: ORD0001 | B2: 2026-07-08 | C2: AMZ | D2: completed | E2: CUS012
A3: ORD0002 | B3: 2026-07-15 | C3: STORE | D3: completed | E3: CUS023
A4: ORD0003 | B4: 2026-07-22 | C4: B2B | D4: cancelled | E4: CUS034
A5: ORD0004 | B5: 2026-07-29 | C5: CN | D5: completed | E5: CUS045
A6: ORD0005 | B6: 2026-08-05 | C6: AMZ | D6: completed | E6: CUS056
A7: ORD0006 | B7: 2026-08-12 | C7: STORE | D7: paid | E7: CUS007
A8: ORD0007 | B8: 2026-08-19 | C8: B2B | D8: completed | E8: CUS018
A9: ORD0008 | B9: 2026-08-26 | C9: CN | D9: completed | E9: CUS029
A10: ORD0009 | B10: 2026-09-02 | C10: AMZ | D10: completed | E10: CUS040
A11: ORD0010 | B11: 2026-09-09 | C11: STORE | D11: completed | E11: CUS051
A12: ORD0011 | B12: 2026-09-16 | C12: B2B | D12: completed | E12: CUS002
... A241: ORD0240 | B241: 2026-07-25 | C241: CN | D241: paid | E241: CUS001

Sheet 商品成本
A1: SKU | B1: 商品名 | C1: 品类 | D1: 单位成本 | E1: 标价 | F1: 重量kg
A2: SKU001 | B2: 清洁喷雾教学型号01 | C2: FMCG | D2: 9.24 | E2: 13 | F2: 0.44
A3: SKU002 | B3: 纸巾教学型号02 | C3: FMCG | D3: 21.77 | E3: 40 | F3: 1.42
A4: SKU003 | B4: 洗衣液教学型号03 | C4: FMCG | D4: 14.86 | E4: 28 | F4: 1.31
A5: SKU004 | B5: 洗手液教学型号04 | C5: FMCG | D5: 13.28 | E5: 25 | F5: 0.87
A6: SKU005 | B6: 厨房湿巾教学型号05 | C6: FMCG | D6: 5.26 | E6: 8 | F6: 0.44
A7: SKU006 | B7: 浴室清洁剂教学型号06 | C7: FMCG | D7: 22.02 | E7: 36 | F7: 0.93
A8: SKU007 | B8: 清洁喷雾教学型号07 | C8: FMCG | D8: 3.58 | E8: 6 | F8: 0.43
A9: SKU008 | B9: 纸巾教学型号08 | C9: FMCG | D9: 5.22 | E9: 9 | F9: 0.62
A10: SKU009 | B10: 洗衣液教学型号09 | C10: FMCG | D10: 13.63 | E10: 26 | F10: 0.69
A11: SKU010 | B11: 洗手液教学型号10 | C11: FMCG | D11: 9.81 | E11: 15 | F11: 0.72
A12: SKU011 | B12: 厨房湿巾教学型号11 | C12: FMCG | D12: 9.69 | E12: 15 | F12: 0.38
A13: SKU012 | B13: 浴室清洁剂教学型号12 | C13: FMCG | D13: 7.05 | E13: 13 | F13: 1.14
... A39: SKU038 | B39: 书架教学型号38 | C39: FURNITURE | D39: 1030.48 | E39: 1470 | F39: 21.04
A40: SKU039 | B40: 边桌教学型号39 | C40: FURNITURE | D40: 921.94 | E40: 1250
A41: SKU040 | B41: 书桌教学型号40 | C41: FURNITURE | D41: 267.69 | E41: 453 | F41: 27.23
A42: SKU041 | B42: 餐椅教学型号41 | C42: FURNITURE | D42: 710.8 | E42: 1273 | F42: 37.53
A43: SKU042 | B43: 沙发教学型号42 | C43: FURNITURE | D43: 986.05 | E43: 1554 | F43: 25.89
A44: SKU043 | B44: 收纳柜教学型号43 | C44: FURNITURE | D44: 397.16 | E44: 755 | F44: 40.65
A45: SKU044 | B45: 书架教学型号44 | C45: FURNITURE | D45: 909.87 | E45: 1290 | F45: 27
A46: SKU045 | B46: 边桌教学型号45 | C46: FURNITURE | D46: 689.03 | E46: 1008 | F46: 17.72
A47: SKU046 | B47: 书桌教学型号46 | C47: FURNITURE | D47: 990.35 | E47: 1657
A48: SKU047 | B48: 餐椅教学型号47 | C48: FURNITURE | D48: 796.52 | E48: 1532 | F48: 22.53
A49: SKU048 | B49: 沙发教学型号48 | C49: FURNITURE | D49: 865.84 | E49: 1309 | F49: 41.53

Sheet 客户分析
A1: 客户ID | B1: 距最近购买天数 | C1: 购买次数 | D1: 观察期净收入 | E1: 首购日期
A2: CUS001 | B2: 39 | C2: 3 | D2: 2034.25 | E2: 46216
A3: CUS002 | B3: 2 | C3: 4 | D3: 3378.95 | E3: 46241
A4: CUS003 | B4: 17 | C4: 4 | D4: 3499.05 | E4: 46226
A5: CUS004 | B5: 32 | C5: 4 | D5: 4540.5 | E5: 46211
A6: CUS005 | B6: 47 | C6: 3 | D6: 3035.75 | E6: 46208
A7: CUS006 | B7: 22 | C7: 2 | D7: 2327.6 | E7: 46233
A8: CUS007 | B8: 37 | C8: 3 | D8: 3376.5 | E8: 46218
A9: CUS008 | B9: 0 | C9: 4 | D9: 876.65 | E9: 46231
A10: CUS009 | B10: 15 | C10: 3 | D10: 2433.2 | E10: 46216
A11: CUS010 | B11: 2 | C11: 3 | D11: 3475.95 | E11: 46213
A12: CUS011 | B12: 45 | C12: 1 | D12: 97.28 | E12: 46250
A13: CUS012 | B13: 20 | C13: 4 | D13: 3512.2 | E13: 46211
... A61: CUS060 | B61: 12 | C61: 4 | D61: 4867.18 | E61: 46231

Sheet 广告日报
A1: 计划 | B1: 日期 | C1: 曝光 | D1: 点击 | E1: 花费 | F1: 归因订单 | G1: 归因销售
A2: CAM01 | B2: 46266 | C2: 1089 | D2: 33 | E2: 31.35 | F2: 2 | G2: 18
A3: CAM01 | B3: 46267 | C3: 1840 | D3: 46 | E3: 71.76 | F3: 5 | G3: 45
A4: CAM01 | B4: 46268 | C4: 1406 | D4: 38 | E4: 59.28 | F4: 1 | G4: 9
A5: CAM01 | B5: 46269 | C5: 621 | D5: 27 | E5: 30.24 | F5: 3 | G5: 27
A6: CAM01 | B6: 46270 | C6: 348 | D6: 12 | E6: 10.92 | F6: 0 | G6: 0
A7: CAM01 | B7: 46271 | C7: 1826 | D7: 83 | E7: 106.24 | F7: 3 | G7: 27
A8: CAM01 | B8: 46272 | C8: 2666 | D8: 86 | E8: 114.38 | F8: 1 | G8: 9
A9: CAM01 | B9: 46273 | C9: 2079 | D9: 63 | E9: 67.41 | F9: 3 | G9: 27
A10: CAM01 | B10: 46274 | C10: 1584 | D10: 48 | E10: 76.32 | F10: 4 | G10: 36
A11: CAM01 | B11: 46275 | C11: 2914 | D11: 62 | E11: 55.18 | F11: 4 | G11: 36
A12: CAM01 | B12: 46276 | C12: 840 | D12: 21 | E12: 31.5 | F12: 2 | G12: 18
A13: CAM01 | B13: 46277 | C13: 1728 | D13: 72 | E13: 49.68 | F13: 1 | G13: 9
... A181: CAM06 | B181: 46295 | C181: 1972 | D181: 68 | E181: 53.04 | F181: 4 | G181: 3020

Sheet 现金流水
A1: 日期 | B1: 类型 | C1: 收付金额
A2: 46204 | B2: 履约支出 | C2: -42
A3: 46204 | B3: 履约支出 | C3: -42
A4: 46205 | B4: 履约支出 | C4: -42
A5: 46205 | B5: 履约支出 | C5: -42
A6: 46206 | B6: 履约支出 | C6: -42
A7: 46207 | B7: 履约支出 | C7: -42
A8: 46207 | B8: 履约支出 | C8: -6.5
A9: 46207 | B9: 履约支出 | C9: -6.5
A10: 46207 | B10: 平台回款 | C10: 1268.78
A11: 46208 | B11: 履约支出 | C11: -42
A12: 46208 | B12: 履约支出 | C12: -6.5
A13: 46208 | B13: 履约支出 | C13: -42
... A673: 46295 | B673: 售后处理支出 | C673: -5

Sheet 原始导入
A1: import_id | B1: business_key | C1: updated_at | D1: amount_cents
A2: IMP01 | B2: BIZ01 | C2: 2026-09-10 10:00:00 | D2: 10000
A3: IMP02 | B3: BIZ01 | C3: 2026-09-10 11:00:00 | D3: 12000
A4: IMP03 | B4: BIZ02 | C4: 2026-09-10 10:00:00 | D4: 8000
A5: IMP04 | B5: BIZ03 | C5: 2026-09-10 10:00:00 | D5: 9000
A6: IMP05 | B6: BIZ03 | C6: 2026-09-10 12:00:00 | D6: 9000

Sheet 任务
A1: ID | B1: 任务 | C1: 题目 | D1: 方式 | E1: 请填写公式或操作记录
A2: EX01 | B2: 销售金额 | C2: 计算首行数量乘单价。 | D2: 公式实操
A3: EX02 | B3: 折后商品金额 | C3: 扣除给定商品折扣。 | D3: 公式实操
A4: EX03 | B4: 广告前贡献 | C4: 扣商品成本、给定佣金和履约费；无其他费用。 | D4: 公式实操
A5: EX04 | B5: 毛利率 | C5: 按折后商品收入计算毛利率，0分母返回0作为此题约定。 | D5: 公式实操
A6: EX05 | B6: 绝对引用费率 | C6: 对第二条输入应用固定F2佣金率，练习锁定引用。 | D6: 公式实操
A7: EX06 | B7: 条件提示 | C7: 此题只检查当前可售是否低于交期需求加安全库存，不作为最终采购建议。 | D7: 公式实操
A8: EX07 | B8: ROAS | C8: 用给定归因销售除广告费。 | D8: 公式实操
A9: EX08 | B9: SUMIF渠道收入 | C9: 汇总CN渠道净商品收入。 | D9: 公式实操
A10: EX09 | B10: SUMIFS期间渠道 | C10: 汇总9月AMZ渠道净商品收入。 | D10: 公式实操
A11: EX10 | B11: COUNTIF取消单 | C11: 统计原始订单cancelled数量。 | D11: 公式实操
A12: EX11 | B12: COUNTIFS渠道状态 | C12: 统计CN且completed的订单。 | D12: 公式实操
A13: EX12 | B13: XLOOKUP成本 | C13: 按输入SKU匹配商品成本；未知SKU返回待核对。 | D13: 公式实操
... A31: EX30 | B31: 输入校验与异常提示 | C31: 为渠道设置有效值，标出缺失成本和负可售数量。 | D31: 界面/转换操作

Sheet 参考答案
A1: ID | B1: 任务 | C1: 说明 | D1: 公式文本 | E1: 实际公式值 | F1: 独立参考值 | G1: 核对
A2: EX01 | B2: 销售金额 | C2: 计算首行数量乘单价。 | D2: ='练习输入'!B2*'练习输入'!C2 -> 0 | E2: ='练习输入'!B2*'练习输入'!C2 -> 26 | F2: 26 | G2: =IF(ABS(E2-F2)<0.00001,"通过","核对") -> 通过
A3: EX02 | B3: 折后商品金额 | C3: 扣除给定商品折扣。 | D3: ='练习输入'!B2*'练习输入'!C2-'练习输入'!D2 -> 0 | E3: ='练习输入'!B2*'练习输入'!C2-'练习输入'!D2 -> 24.7 | F3: 24.7 | G3: =IF(ABS(E3-F3)<0.00001,"通过","核对") -> 通过
A4: EX03 | B4: 广告前贡献 | C4: 扣商品成本、给定佣金和履约费；无其他费用。 | D4: =('练习输入'!B2*'练习输入'!C2-'练习输入'!D2)-'练习输入'!B2*'练习输入'!E2-('练习输入'!B2*'练习输入'!C2-'练习输入'!D2)*'练习输入'!F2-'练习输入'!G2 -> 0 | E4: =('练习输入'!B2*'练习输入'!C2-'练习输入'!D2)-'练习输入'!B2*'练习输入'!E2-('练习输入'!B2*'练习输入'!C2-'练习输入'!D2)*'练习输入'!F2-'练习输入'!G2 -> -1.762 | F4: -1.762 | G4: =IF(ABS(E4-F4)<0.00001,"通过","核对") -> 通过
A5: EX04 | B5: 毛利率 | C5: 按折后商品收入计算毛利率，0分母返回0作为此题约定。 | D5: =IFERROR(('练习输入'!B2*'练习输入'!C2-'练习输入'!D2-'练习输入'!B2*'练习输入'!E2)/('练习输入'!B2*'练习输入'!C2-'练习输入'!D2),0) -> 0 | E5: =IFERROR(('练习输入'!B2*'练习输入'!C2-'练习输入'!D2-'练习输入'!B2*'练习输入'!E2)/('练习输入'!B2*'练习输入'!C2-'练习输入'!D2),0) -> 0.25182186 | F5: 0.25182186 | G5: =IF(ABS(E5-F5)<0.00001,"通过","核对") -> 通过
A6: EX05 | B6: 绝对引用费率 | C6: 对第二条输入应用固定F2佣金率，练习锁定引用。 | D6: =('练习输入'!B3*'练习输入'!C3-'练习输入'!D3)*'练习输入'!$F$2 -> 0 | E6: =('练习输入'!B3*'练习输入'!C3-'练习输入'!D3)*'练习输入'!$F$2 -> 4.56 | F6: 4.56 | G6: =IF(ABS(E6-F6)<0.00001,"通过","核对") -> 通过
A7: EX06 | B7: 条件提示 | C7: 此题只检查当前可售是否低于交期需求加安全库存，不作为最终采购建议。 | D7: =IF('练习输入'!L2<'练习输入'!M2*'练习输入'!N2+'练习输入'!O2,"需评估补货","暂不补货") -> 0 | E7: =IF('练习输入'!L2<'练习输入'!M2*'练习输入'!N2+'练习输入'!O2,"需评估补货","暂不补货") -> 需评估补货 | F7: 需评估补货 | G7: =IF(E7=F7,"通过","核对") -> 通过
A8: EX07 | B8: ROAS | C8: 用给定归因销售除广告费。 | D8: =IFERROR('练习输入'!K2/'练习输入'!J2,0) -> 0 | E8: =IFERROR('练习输入'!K2/'练习输入'!J2,0) -> 4 | F8: 4 | G8: =IF(ABS(E8-F8)<0.00001,"通过","核对") -> 通过
A9: EX08 | B9: SUMIF渠道收入 | C9: 汇总CN渠道净商品收入。 | D9: =SUMIF('订单财务'!C2:C199,"CN",'订单财务'!D2:D199) -> 0 | E9: =SUMIF('订单财务'!C2:C199,"CN",'订单财务'!D2:D199) -> 46324.45 | F9: 46324.45 | G9: =IF(ABS(E9-F9)<0.00001,"通过","核对") -> 通过
A10: EX09 | B10: SUMIFS期间渠道 | C10: 汇总9月AMZ渠道净商品收入。 | D10: =SUMIFS('订单财务'!D2:D199,'订单财务'!C2:C199,"AMZ",'订单财务'!B2:B199,">="&DATE(2026,9,1)) -> 0 | E10: =SUMIFS('订单财务'!D2:D199,'订单财务'!C2:C199,"AMZ",'订单财务'!B2:B199,">="&DATE(2026,9,1)) -> 21364.41 | F10: 21364.41 | G10: =IF(ABS(E10-F10)<0.00001,"通过","核对") -> 通过
A11: EX10 | B11: COUNTIF取消单 | C11: 统计原始订单cancelled数量。 | D11: =COUNTIF('原始订单'!D2:D241,"cancelled") -> 0 | E11: =COUNTIF('原始订单'!D2:D241,"cancelled") -> 26 | F11: 26 | G11: =IF(ABS(E11-F11)<0.00001,"通过","核对") -> 通过
A12: EX11 | B12: COUNTIFS渠道状态 | C12: 统计CN且completed的订单。 | D12: =COUNTIFS('原始订单'!C2:C241,"CN",'原始订单'!D2:D241,"completed") -> 0 | E12: =COUNTIFS('原始订单'!C2:C241,"CN",'原始订单'!D2:D241,"completed") -> 30 | F12: 30 | G12: =IF(ABS(E12-F12)<0.00001,"通过","核对") -> 通过
A13: EX12 | B13: XLOOKUP成本 | C13: 按输入SKU匹配商品成本；未知SKU返回待核对。 | D13: {=_xlfn.XLOOKUP('练习输入'!A2,'商品成本'!A2:A49,'商品成本'!D2:D49,"待核对")} -> 0 | E13: {=_xlfn.XLOOKUP('练习输入'!A2,'商品成本'!A2:A49,'商品成本'!D2:D49,"待核对")} -> 9.24 | F13: 9.24 | G13: =IF(ABS(E13-F13)<0.00001,"通过","核对") -> 通过
A14: EX13 | B14: VLOOKUP对照 | C14: 以精确匹配完成同一成本查找。 | D14: =VLOOKUP('练习输入'!A2,'商品成本'!A2:E49,4,FALSE) -> 0 | E14: =VLOOKUP('练习输入'!A2,'商品成本'!A2:E49,4,FALSE) -> 9.24 | F14: 9.24 | G14: =IF(ABS(E14-F14)<0.00001,"通过","核对") -> 通过
A15: EX14 | B15: 重复键检查 | C15: 检查原始导入BIZ01出现次数。 | D15: =COUNTIF('原始导入'!B2:B6,"BIZ01") -> 0 | E15: =COUNTIF('原始导入'!B2:B6,"BIZ01") -> 2 | F15: 2 | G15: =IF(ABS(E15-F15)<0.00001,"通过","核对") -> 通过
A16: EX15 | B16: TRIM清理 | C16: 清理输入SKU两端空格，保留原列。 | D16: =TRIM('练习输入'!R2) -> 0 | E16: =TRIM('练习输入'!R2) -> SKU001 | F16: SKU001 | G16: =IF(E16=F16,"通过","核对") -> 通过
A17: EX16 | B17: 日期标准化 | C17: 将输入文本日期转成yyyy-mm月份标签。 | D17: =TEXT(DATEVALUE('练习输入'!S2),"yyyy-mm") -> 0 | E17: =TEXT(DATEVALUE('练习输入'!S2),"yyyy-mm") -> 2026-09 | F17: 2026-09 | G17: =IF(E17=F17,"通过","核对") -> 通过
A18: EX17 | B18: RFM近度标签 | C18: 客户第一行距最近购买不超过30天则标近期。 | D18: =IF('客户分析'!B2<=30,"近期","较久") -> 0 | E18: =IF('客户分析'!B2<=30,"近期","较久") -> 较久 | F18: 较久 | G18: =IF(E18=F18,"通过","核对") -> 通过
A19: EX18 | B19: 加权点击率 | C19: 先汇总点击曝光，再计算总体CTR。 | D19: =SUM('广告日报'!D2:D181)/SUM('广告日报'!C2:C181) -> 0 | E19: =SUM('广告日报'!D2:D181)/SUM('广告日报'!C2:C181) -> 0.028162223 | F19: 0.028162223 | G19: =IF(ABS(E19-F19)<0.00001,"通过","核对") -> 通过
A20: EX19 | B20: 退款净额核对 | C20: 汇总折后退款前金额减退款，核对净商品收入。 | D20: =SUM('订单财务'!L2:L199)-SUM('订单财务'!M2:M199) -> 0 | E20: =SUM('订单财务'!L2:L199)-SUM('订单财务'!M2:M199) -> 186961.63 | F20: 186961.63 | G20: =IF(ABS(E20-F20)<0.00001,"通过","核对") -> 通过
A21: EX20 | B21: 广告预算偏差 | C21: 预算为教学假设12000元，计算实际减预算。 | D21: =SUM('广告日报'!E2:E181)-12000 -> 0 | E21: =SUM('广告日报'!E2:E181)-12000 -> -1100.22 | F21: -1100.22 | G21: =IF(ABS(E21-F21)<0.00001,"通过","核对") -> 通过
A22: EX21 | B22: 含在途与MOQ补货 | C22: 按输入首行计算补货量；available已扣预留，MOQ向上取整。 | D22: =MAX(0,CEILING(('练习输入'!M2*'练习输入'!N2+'练习输入'!O2-'练习输入'!L2-'练习输入'!Q2)/'练习输入'!P2,1)*'练习输入'!P2) -> 0 | E22: =MAX(0,CEILING(('练习输入'!M2*'练习输入'!N2+'练习输入'!O2-'练习输入'!L2-'练习输入'!Q2)/'练习输入'!P2,1)*'练习输入'!P2) -> 24 | F22: 24 | G22: =IF(ABS(E22-F22)<0.00001,"通过","核对") -> 通过
A23: EX22 | B23: 现金余额 | C23: 期初现金100000元，加实际收付流水。 | D23: =100000+SUM('现金流水'!C2:C673) -> 0 | E23: =100000+SUM('现金流水'!C2:C673) -> 201503.85 | F23: 201503.85 | G23: =IF(ABS(E23-F23)<0.00001,"通过","核对") -> 通过
A24: EX23 | B24: 成熟客户数 | C24: 计算首购不晚于2026-08-31的客户数量。 | D24: =COUNTIF('客户分析'!E2:E61,"<="&DATE(2026,8,31)) -> 0 | E24: =COUNTIF('客户分析'!E2:E61,"<="&DATE(2026,8,31)) -> 60 | F24: 60 | G24: =IF(ABS(E24-F24)<0.00001,"通过","核对") -> 通过
A25: EX24 | B25: 透视切片核对 | C25: 用SUMIFS核对9月CN广告前贡献；再用透视表实现同一切片。 | D25: =SUMIFS('订单财务'!J2:J199,'订单财务'!C2:C199,"CN",'订单财务'!B2:B199,">="&DATE(2026,9,1)) -> 0 | E25: =SUMIFS('订单财务'!J2:J199,'订单财务'!C2:C199,"CN",'订单财务'!B2:B199,">="&DATE(2026,9,1)) -> 1849.55 | F25: 1849.55 | G25: =IF(ABS(E25-F25)<0.00001,"通过","核对") -> 通过
A26: EX25 | B26: 原生透视表 | C26: 以订单财务为数据源；渠道为行，日期为筛选，净商品收入与贡献为求和。 | D26: 检查总计与参考数据一致，比率另用汇总分子分母计算。 | E26: 需人工操作 | F26: 按验收条件核对 | G26: 未实测
A27: EX26 | B27: 合并商品成本 | C27: 使用Power Query合并订单明细与商品表，先检查SKU唯一性。 | D27: 展开后行数不意外增加；未匹配SKU单独显示。 | E27: 需人工操作 | F27: 按验收条件核对 | G27: 未实测
A28: EX27 | B28: 追加月度表 | C28: 将同结构月度文件按列名追加，检查金额单位和日期类型。 | D28: 总记录数与各月之和一致，重复导入可识别。 | E28: 需人工操作 | F28: 按验收条件核对 | G28: 未实测
A29: EX28 | B29: 逆透视月份 | C29: 把按月份横向展开的销量表转为SKU、月份、销量长表。 | D29: SKU月份组合唯一，不把总计列当月份。 | E29: 需人工操作 | F29: 按验收条件核对 | G29: 未实测
A30: EX29 | B30: 经营图表与汇报 | C30: 做渠道贡献条形图和按日趋势图，并写一条有证据的动作建议。 | D30: 轴、单位、日期与口径完整；不把相关变化写成因果。 | E30: 需人工操作 | F30: 按验收条件核对 | G30: 未实测
A31: EX30 | B31: 输入校验与异常提示 | C31: 为渠道设置有效值，标出缺失成本和负可售数量。 | D31: 错误输入可见并可追踪，不能用填0掩盖缺失。 | E31: 需人工操作 | F31: 按验收条件核对 | G31: 未实测
